tejask/__init__.py
tejask-0.0.1.dist-info/LICENSE.txt
tejask-0.0.1.dist-info/METADATA
tejask-0.0.1.dist-info/WHEEL
tejask-0.0.1.dist-info/top_level.txt
tejask-0.0.1.dist-info/RECORD
