Metadata-Version: 2.1
Name: tejask
Version: 0.0.1
Summary: This module has methods like add, sub, mult, div, ascend, descend
Home-page: https://github.com/Pushkar-Singh-14/
Author: Tejas
Author-email: tejk7167@gmail.com
License: UNKNOWN
Platform: UNKNOWN
Classifier: Programming Language :: Python :: 3
Classifier: License :: OSI Approved :: MIT License
Classifier: Operating System :: OS Independent
